Workbook

Sheet Dashboard
B2: Corner Shop: Sales & Stock Dashboard
B3: Jul-Sep 2026 | DEMO DATA
B5: Total revenue | C5: Total profit | D5: Profit margin | E5: Items to reorder
B6: =SUM(Stock!J2:J13) -> 1019.04 | C6: =SUM(Stock!K2:K13) -> 426.79 | D6: =IFERROR(C6/B6,0) -> 0.41881575 | E6: =COUNTIF(Stock!I2:I13,"REORDER") -> 4
B8: Top 5 products by revenue | H8: Needs reordering
B9: Product | C9: Revenue (£) | D9: Units sold | H9: Product | I9: Stock left
B10: =INDEX(Stock!$A$2:$A$13,MATCH(LARGE(Stock!$L$2:$L$13,1),Stock!$L$2:$L$13,0)) -> Cheddar 400g | C10: =INDEX(Stock!$J$2:$J$13,MATCH(LARGE(Stock!$L$2:$L$13,1),Stock!$L$2:$L$13,0)) -> 135.3 | D10: =INDEX(Stock!$F$2:$F$13,MATCH(LARGE(Stock!$L$2:$L$13,1),Stock!$L$2:$L$13,0)) -> 41 | H10: =IFERROR(INDEX(Stock!$A$2:$A$13,MATCH(1,Stock!$M$2:$M$13,0)),"") -> Cheddar 400g | I10: =IFERROR(INDEX(Stock!$G$2:$G$13,MATCH(1,Stock!$M$2:$M$13,0)),"") -> 5
B11: =INDEX(Stock!$A$2:$A$13,MATCH(LARGE(Stock!$L$2:$L$13,2),Stock!$L$2:$L$13,0)) -> Crisps Multipack | C11: =INDEX(Stock!$J$2:$J$13,MATCH(LARGE(Stock!$L$2:$L$13,2),Stock!$L$2:$L$13,0)) -> 105.6 | D11: =INDEX(Stock!$F$2:$F$13,MATCH(LARGE(Stock!$L$2:$L$13,2),Stock!$L$2:$L$13,0)) -> 44 | H11: =IFERROR(INDEX(Stock!$A$2:$A$13,MATCH(2,Stock!$M$2:$M$13,0)),"") -> White Bread | I11: =IFERROR(INDEX(Stock!$G$2:$G$13,MATCH(2,Stock!$M$2:$M$13,0)),"") -> 3
B12: =INDEX(Stock!$A$2:$A$13,MATCH(LARGE(Stock!$L$2:$L$13,3),Stock!$L$2:$L$13,0)) -> Biscuits 300g | C12: =INDEX(Stock!$J$2:$J$13,MATCH(LARGE(Stock!$L$2:$L$13,3),Stock!$L$2:$L$13,0)) -> 100.5 | D12: =INDEX(Stock!$F$2:$F$13,MATCH(LARGE(Stock!$L$2:$L$13,3),Stock!$L$2:$L$13,0)) -> 67 | H12: =IFERROR(INDEX(Stock!$A$2:$A$13,MATCH(3,Stock!$M$2:$M$13,0)),"") -> Croissant 4-pack | I12: =IFERROR(INDEX(Stock!$G$2:$G$13,MATCH(3,Stock!$M$2:$M$13,0)),"") -> 6
B13: =INDEX(Stock!$A$2:$A$13,MATCH(LARGE(Stock!$L$2:$L$13,4),Stock!$L$2:$L$13,0)) -> Tea Bags 80s | C13: =INDEX(Stock!$J$2:$J$13,MATCH(LARGE(Stock!$L$2:$L$13,4),Stock!$L$2:$L$13,0)) -> 98.8 | D13: =INDEX(Stock!$F$2:$F$13,MATCH(LARGE(Stock!$L$2:$L$13,4),Stock!$L$2:$L$13,0)) -> 52 | H13: =IFERROR(INDEX(Stock!$A$2:$A$13,MATCH(4,Stock!$M$2:$M$13,0)),"") -> Pasta 500g | I13: =IFERROR(INDEX(Stock!$G$2:$G$13,MATCH(4,Stock!$M$2:$M$13,0)),"") -> 4
B14: =INDEX(Stock!$A$2:$A$13,MATCH(LARGE(Stock!$L$2:$L$13,5),Stock!$L$2:$L$13,0)) -> Sparkling Water 6x | C14: =INDEX(Stock!$J$2:$J$13,MATCH(LARGE(Stock!$L$2:$L$13,5),Stock!$L$2:$L$13,0)) -> 96.2 | D14: =INDEX(Stock!$F$2:$F$13,MATCH(LARGE(Stock!$L$2:$L$13,5),Stock!$L$2:$L$13,0)) -> 37 | H14: =IFERROR(INDEX(Stock!$A$2:$A$13,MATCH(5,Stock!$M$2:$M$13,0)),"") | I14: =IFERROR(INDEX(Stock!$G$2:$G$13,MATCH(5,Stock!$M$2:$M$13,0)),"")
H15: =IFERROR(INDEX(Stock!$A$2:$A$13,MATCH(6,Stock!$M$2:$M$13,0)),"") | I15: =IFERROR(INDEX(Stock!$G$2:$G$13,MATCH(6,Stock!$M$2:$M$13,0)),"")
B17: Revenue by month
B18: Month start | C18: Revenue (£)
B19: 46204 | C19: =SUMIFS(Sales!$E$2:$E$168,Sales!$A$2:$A$168,">="&B19,Sales!$A$2:$A$168,"<"&EDATE(B19,1)) -> 299.58
B20: 46235 | C20: =SUMIFS(Sales!$E$2:$E$168,Sales!$A$2:$A$168,">="&B20,Sales!$A$2:$A$168,"<"&EDATE(B20,1)) -> 361.58
B21: 46266 | C21: =SUMIFS(Sales!$E$2:$E$168,Sales!$A$2:$A$168,">="&B21,Sales!$A$2:$A$168,"<"&EDATE(B21,1)) -> 357.88
B24: Revenue by category
B25: Category | C25: Revenue (£)
B26: Dairy | C26: =SUMIFS(Stock!$J$2:$J$13,Stock!$B$2:$B$13,B26) -> 222.75
B27: Bakery | C27: =SUMIFS(Stock!$J$2:$J$13,Stock!$B$2:$B$13,B27) -> 124.8
B28: Drinks | C28: =SUMIFS(Stock!$J$2:$J$13,Stock!$B$2:$B$13,B28) -> 192.2
B29: Grocery | C29: =SUMIFS(Stock!$J$2:$J$13,Stock!$B$2:$B$13,B29) -> 193
B30: Snacks | C30: =SUMIFS(Stock!$J$2:$J$13,Stock!$B$2:$B$13,B30) -> 286.29

Sheet Stock
A1: Product | B1: Category | C1: Cost (£) | D1: Price (£) | E1: Opening stock | F1: Units sold | G1: Stock left | H1: Reorder at | I1: Status | J1: Revenue (£) | K1: Profit (£) | L1: Rank helper | M1: Reorder # | O1: Note
A2: Whole Milk 2L | B2: Dairy | C2: 1.1 | D2: 1.65 | E2: 70 | F2: =SUMIFS(Sales!$C$2:$C$168,Sales!$B$2:$B$168,A2) -> 53 | G2: =E2-F2 -> 17 | H2: 12 | I2: =IF(G2<=H2,"REORDER","OK") -> OK | J2: =F2*D2 -> 87.45 | K2: =F2*(D2-C2) -> 29.15 | L2: =J2+ROW()/1000000 -> 87.450002 | M2: =IF(I2="REORDER",COUNTIF($I$2:I2,"REORDER"),"")
A3: Cheddar 400g | B3: Dairy | C3: 2.2 | D3: 3.3 | E3: 46 | F3: =SUMIFS(Sales!$C$2:$C$168,Sales!$B$2:$B$168,A3) -> 41 | G3: =E3-F3 -> 5 | H3: 6 | I3: =IF(G3<=H3,"REORDER","OK") -> REORDER | J3: =F3*D3 -> 135.3 | K3: =F3*(D3-C3) -> 45.1 | L3: =J3+ROW()/1000000 -> 135.3 | M3: =IF(I3="REORDER",COUNTIF($I$2:I3,"REORDER"),"") -> 1
A4: White Bread | B4: Bakery | C4: 0.7 | D4: 1.2 | E4: 52 | F4: =SUMIFS(Sales!$C$2:$C$168,Sales!$B$2:$B$168,A4) -> 49 | G4: =E4-F4 -> 3 | H4: 12 | I4: =IF(G4<=H4,"REORDER","OK") -> REORDER | J4: =F4*D4 -> 58.8 | K4: =F4*(D4-C4) -> 24.5 | L4: =J4+ROW()/1000000 -> 58.800004 | M4: =IF(I4="REORDER",COUNTIF($I$2:I4,"REORDER"),"") -> 2
A5: Croissant 4-pack | B5: Bakery | C5: 1.3 | D5: 2.2 | E5: 36 | F5: =SUMIFS(Sales!$C$2:$C$168,Sales!$B$2:$B$168,A5) -> 30 | G5: =E5-F5 -> 6 | H5: 8 | I5: =IF(G5<=H5,"REORDER","OK") -> REORDER | J5: =F5*D5 -> 66 | K5: =F5*(D5-C5) -> 27 | L5: =J5+ROW()/1000000 -> 66.000005 | M5: =IF(I5="REORDER",COUNTIF($I$2:I5,"REORDER"),"") -> 3
A6: Orange Juice 1L | B6: Drinks | C6: 1.2 | D6: 2 | E6: 63 | F6: =SUMIFS(Sales!$C$2:$C$168,Sales!$B$2:$B$168,A6) -> 48 | G6: =E6-F6 -> 15 | H6: 10 | I6: =IF(G6<=H6,"REORDER","OK") -> OK | J6: =F6*D6 -> 96 | K6: =F6*(D6-C6) -> 38.4 | L6: =J6+ROW()/1000000 -> 96.000006 | M6: =IF(I6="REORDER",COUNTIF($I$2:I6,"REORDER"),"")
A7: Sparkling Water 6x | B7: Drinks | C7: 1.6 | D7: 2.6 | E7: 56 | F7: =SUMIFS(Sales!$C$2:$C$168,Sales!$B$2:$B$168,A7) -> 37 | G7: =E7-F7 -> 19 | H7: 8 | I7: =IF(G7<=H7,"REORDER","OK") -> OK | J7: =F7*D7 -> 96.2 | K7: =F7*(D7-C7) -> 37 | L7: =J7+ROW()/1000000 -> 96.200007 | M7: =IF(I7="REORDER",COUNTIF($I$2:I7,"REORDER"),"")
A8: Tea Bags 80s | B8: Grocery | C8: 1 | D8: 1.9 | E8: 74 | F8: =SUMIFS(Sales!$C$2:$C$168,Sales!$B$2:$B$168,A8) -> 52 | G8: =E8-F8 -> 22 | H8: 10 | I8: =IF(G8<=H8,"REORDER","OK") -> OK | J8: =F8*D8 -> 98.8 | K8: =F8*(D8-C8) -> 46.8 | L8: =J8+ROW()/1000000 -> 98.800008 | M8: =IF(I8="REORDER",COUNTIF($I$2:I8,"REORDER"),"")
A9: Pasta 500g | B9: Grocery | C9: 0.5 | D9: 1.05 | E9: 38 | F9: =SUMIFS(Sales!$C$2:$C$168,Sales!$B$2:$B$168,A9) -> 34 | G9: =E9-F9 -> 4 | H9: 10 | I9: =IF(G9<=H9,"REORDER","OK") -> REORDER | J9: =F9*D9 -> 35.7 | K9: =F9*(D9-C9) -> 18.7 | L9: =J9+ROW()/1000000 -> 35.700009 | M9: =IF(I9="REORDER",COUNTIF($I$2:I9,"REORDER"),"") -> 4
A10: Rice 1kg | B10: Grocery | C10: 1.1 | D10: 1.95 | E10: 57 | F10: =SUMIFS(Sales!$C$2:$C$168,Sales!$B$2:$B$168,A10) -> 30 | G10: =E10-F10 -> 27 | H10: 8 | I10: =IF(G10<=H10,"REORDER","OK") -> OK | J10: =F10*D10 -> 58.5 | K10: =F10*(D10-C10) -> 25.5 | L10: =J10+ROW()/1000000 -> 58.50001 | M10: =IF(I10="REORDER",COUNTIF($I$2:I10,"REORDER"),"")
A11: Crisps Multipack | B11: Snacks | C11: 1.4 | D11: 2.4 | E11: 66 | F11: =SUMIFS(Sales!$C$2:$C$168,Sales!$B$2:$B$168,A11) -> 44 | G11: =E11-F11 -> 22 | H11: 12 | I11: =IF(G11<=H11,"REORDER","OK") -> OK | J11: =F11*D11 -> 105.6 | K11: =F11*(D11-C11) -> 44 | L11: =J11+ROW()/1000000 -> 105.60001 | M11: =IF(I11="REORDER",COUNTIF($I$2:I11,"REORDER"),"")
A12: Chocolate Bar | B12: Snacks | C12: 0.45 | D12: 0.99 | E12: 107 | F12: =SUMIFS(Sales!$C$2:$C$168,Sales!$B$2:$B$168,A12) -> 81 | G12: =E12-F12 -> 26 | H12: 15 | I12: =IF(G12<=H12,"REORDER","OK") -> OK | J12: =F12*D12 -> 80.19 | K12: =F12*(D12-C12) -> 43.74 | L12: =J12+ROW()/1000000 -> 80.190012 | M12: =IF(I12="REORDER",COUNTIF($I$2:I12,"REORDER"),"")
A13: Biscuits 300g | B13: Snacks | C13: 0.8 | D13: 1.5 | E13: 92 | F13: =SUMIFS(Sales!$C$2:$C$168,Sales!$B$2:$B$168,A13) -> 67 | G13: =E13-F13 -> 25 | H13: 8 | I13: =IF(G13<=H13,"REORDER","OK") -> OK | J13: =F13*D13 -> 100.5 | K13: =F13*(D13-C13) -> 46.9 | L13: =J13+ROW()/1000000 -> 100.50001 | M13: =IF(I13="REORDER",COUNTIF($I$2:I13,"REORDER"),"")

Sheet Sales
A1: Date | B1: Product | C1: Qty | D1: Unit price (£) | E1: Revenue (£) | G1: How to use
A2: 46204 | B2: Biscuits 300g | C2: 4 | D2: =INDEX(Stock!$D$2:$D$13,MATCH(B2,Stock!$A$2:$A$13,0)) -> 1.5 | E2: =C2*D2 -> 6
A3: 46204 | B3: Rice 1kg | C3: 1 | D3: =INDEX(Stock!$D$2:$D$13,MATCH(B3,Stock!$A$2:$A$13,0)) -> 1.95 | E3: =C3*D3 -> 1.95
A4: 46205 | B4: Whole Milk 2L | C4: 5 | D4: =INDEX(Stock!$D$2:$D$13,MATCH(B4,Stock!$A$2:$A$13,0)) -> 1.65 | E4: =C4*D4 -> 8.25
A5: 46205 | B5: Whole Milk 2L | C5: 5 | D5: =INDEX(Stock!$D$2:$D$13,MATCH(B5,Stock!$A$2:$A$13,0)) -> 1.65 | E5: =C5*D5 -> 8.25
A6: 46205 | B6: White Bread | C6: 1 | D6: =INDEX(Stock!$D$2:$D$13,MATCH(B6,Stock!$A$2:$A$13,0)) -> 1.2 | E6: =C6*D6 -> 1.2
A7: 46206 | B7: Orange Juice 1L | C7: 2 | D7: =INDEX(Stock!$D$2:$D$13,MATCH(B7,Stock!$A$2:$A$13,0)) -> 2 | E7: =C7*D7 -> 4
A8: 46206 | B8: Whole Milk 2L | C8: 4 | D8: =INDEX(Stock!$D$2:$D$13,MATCH(B8,Stock!$A$2:$A$13,0)) -> 1.65 | E8: =C8*D8 -> 6.6
A9: 46207 | B9: Chocolate Bar | C9: 1 | D9: =INDEX(Stock!$D$2:$D$13,MATCH(B9,Stock!$A$2:$A$13,0)) -> 0.99 | E9: =C9*D9 -> 0.99
A10: 46208 | B10: Pasta 500g | C10: 5 | D10: =INDEX(Stock!$D$2:$D$13,MATCH(B10,Stock!$A$2:$A$13,0)) -> 1.05 | E10: =C10*D10 -> 5.25
A11: 46209 | B11: Pasta 500g | C11: 4 | D11: =INDEX(Stock!$D$2:$D$13,MATCH(B11,Stock!$A$2:$A$13,0)) -> 1.05 | E11: =C11*D11 -> 4.2
A12: 46210 | B12: Biscuits 300g | C12: 1 | D12: =INDEX(Stock!$D$2:$D$13,MATCH(B12,Stock!$A$2:$A$13,0)) -> 1.5 | E12: =C12*D12 -> 1.5
A13: 46211 | B13: Chocolate Bar | C13: 3 | D13: =INDEX(Stock!$D$2:$D$13,MATCH(B13,Stock!$A$2:$A$13,0)) -> 0.99 | E13: =C13*D13 -> 2.97
... A168: 46295 | B168: Biscuits 300g | C168: 2 | D168: =INDEX(Stock!$D$2:$D$13,MATCH(B168,Stock!$A$2:$A$13,0)) -> 1.5 | E168: =C168*D168 -> 3
